{
  "minecraft:acacia_button": "wood",
  "minecraft:acacia_door": "wood",
  "minecraft:acacia_double_slab": "wood",
  "minecraft:acacia_fence": "wood",
  "minecraft:acacia_fence_gate": "wood",
  "minecraft:acacia_hanging_sign": "hanging_sign",
  "minecraft:acacia_leaves": "grass",
  "minecraft:acacia_log": "wood",
  "minecraft:acacia_pressure_plate": "wood",
  "minecraft:acacia_sapling": "grass",
  "minecraft:acacia_slab": "wood",
  "minecraft:acacia_stairs": "wood",
  "minecraft:acacia_standing_sign": "wood",
  "minecraft:acacia_trapdoor": "wood",
  "minecraft:acacia_wall_sign": "wood",
  "minecraft:acacia_wood": "wood",
  "minecraft:activator_rail": "metal",
  "minecraft:allium": "grass",
  "minecraft:allow": "stone",
  "minecraft:amethyst_block": "amethyst_block",
  "minecraft:amethyst_cluster": "amethyst_cluster",
  "minecraft:ancient_debris": "ancient_debris",
  "minecraft:andesite": "stone",
  "minecraft:andesite_double_slab": "stone",
  "minecraft:andesite_slab": "stone",
  "minecraft:andesite_stairs": "stone",
  "minecraft:andesite_wall": "stone",
  "minecraft:anvil": "anvil",
  "minecraft:azalea": "azalea",
  "minecraft:azalea_leaves": "azalea_leaves",
  "minecraft:azalea_leaves_flowered": "azalea_leaves",
  "minecraft:azure_bluet": "grass",
  "minecraft:bamboo": "bamboo",
  "minecraft:bamboo_block": "bamboo_wood",
  "minecraft:bamboo_button": "bamboo_wood",
  "minecraft:bamboo_door": "bamboo_wood",
  "minecraft:bamboo_double_slab": "bamboo_wood",
  "minecraft:bamboo_fence": "bamboo_wood",
  "minecraft:bamboo_fence_gate": "bamboo_wood",
  "minecraft:bamboo_hanging_sign": "bamboo_wood_hanging_sign",
  "minecraft:bamboo_mosaic": "bamboo_wood",
  "minecraft:bamboo_mosaic_double_slab": "bamboo_wood",
  "minecraft:bamboo_mosaic_slab": "bamboo_wood",
  "minecraft:bamboo_mosaic_stairs": "bamboo_wood",
  "minecraft:bamboo_planks": "bamboo_wood",
  "minecraft:bamboo_pressure_plate": "bamboo_wood",
  "minecraft:bamboo_sapling": "bamboo_sapling",
  "minecraft:bamboo_slab": "bamboo_wood",
  "minecraft:bamboo_stairs": "bamboo_wood",
  "minecraft:bamboo_standing_sign": "bamboo_wood",
  "minecraft:bamboo_trapdoor": "bamboo_wood",
  "minecraft:bamboo_wall_sign": "bamboo_wood",
  "minecraft:barrel": "wood",
  "minecraft:basalt": "basalt",
  "minecraft:beacon": "glass",
  "minecraft:bed": "wood",
  "minecraft:bedrock": "stone",
  "minecraft:beetroot": "wood",
  "minecraft:bell": "metal",
  "minecraft:big_dripleaf": "big_dripleaf",
  "minecraft:birch_button": "wood",
  "minecraft:birch_door": "wood",
  "minecraft:birch_double_slab": "wood",
  "minecraft:birch_fence": "wood",
  "minecraft:birch_fence_gate": "wood",
  "minecraft:birch_hanging_sign": "hanging_sign",
  "minecraft:birch_leaves": "grass",
  "minecraft:birch_log": "wood",
  "minecraft:birch_pressure_plate": "wood",
  "minecraft:birch_sapling": "grass",
  "minecraft:birch_slab": "wood",
  "minecraft:birch_stairs": "wood",
  "minecraft:birch_standing_sign": "wood",
  "minecraft:birch_trapdoor": "wood",
  "minecraft:birch_wall_sign": "wood",
  "minecraft:birch_wood": "wood",
  "minecraft:black_candle": "candle",
  "minecraft:black_candle_cake": "cloth",
  "minecraft:black_carpet": "cloth",
  "minecraft:black_concrete": "stone",
  "minecraft:black_concrete_powder": "sand",
  "minecraft:black_glazed_terracotta": "stone",
  "minecraft:black_shulker_box": "stone",
  "minecraft:black_stained_glass": "glass",
  "minecraft:black_stained_glass_pane": "glass",
  "minecraft:black_terracotta": "stone",
  "minecraft:black_wool": "cloth",
  "minecraft:blackstone": "stone",
  "minecraft:blackstone_double_slab": "stone",
  "minecraft:blackstone_slab": "stone",
  "minecraft:blackstone_stairs": "stone",
  "minecraft:blackstone_wall": "stone",
  "minecraft:blast_furnace": "stone",
  "minecraft:blue_candle": "candle",
  "minecraft:blue_candle_cake": "cloth",
  "minecraft:blue_carpet": "cloth",
  "minecraft:blue_concrete": "stone",
  "minecraft:blue_concrete_powder": "sand",
  "minecraft:blue_glazed_terracotta": "stone",
  "minecraft:blue_ice": "glass",
  "minecraft:blue_orchid": "grass",
  "minecraft:blue_shulker_box": "stone",
  "minecraft:blue_stained_glass": "glass",
  "minecraft:blue_stained_glass_pane": "glass",
  "minecraft:blue_terracotta": "stone",
  "minecraft:blue_wool": "cloth",
  "minecraft:bone_block": "bone_block",
  "minecraft:bookshelf": "wood",
  "minecraft:border_block": "stone",
  "minecraft:brain_coral": "stone",
  "minecraft:brain_coral_block": "stone",
  "minecraft:brain_coral_fan": "stone",
  "minecraft:brain_coral_wall_fan": "stone",
  "minecraft:brewing_stand": "stone",
  "minecraft:brick_double_slab": "stone",
  "minecraft:brick_slab": "stone",
  "minecraft:brick_wall": "stone",
  "minecraft:brown_candle": "candle",
  "minecraft:brown_candle_cake": "cloth",
  "minecraft:brown_carpet": "cloth",
  "minecraft:brown_concrete": "stone",
  "minecraft:brown_concrete_powder": "sand",
  "minecraft:brown_glazed_terracotta": "stone",
  "minecraft:brown_mushroom": "grass",
  "minecraft:brown_mushroom_block": "wood",
  "minecraft:brown_shulker_box": "stone",
  "minecraft:brown_stained_glass": "glass",
  "minecraft:brown_stained_glass_pane": "glass",
  "minecraft:brown_terracotta": "stone",
  "minecraft:brown_wool": "cloth",
  "minecraft:bubble_coral": "stone",
  "minecraft:bubble_coral_block": "stone",
  "minecraft:bubble_coral_fan": "stone",
  "minecraft:bubble_coral_wall_fan": "stone",
  "minecraft:budding_amethyst": "amethyst_block",
  "minecraft:cactus": "cloth",
  "minecraft:cake": "cloth",
  "minecraft:calcite": "calcite",
  "minecraft:calibrated_sculk_sensor": "sculk_sensor",
  "minecraft:campfire": "wood",
  "minecraft:candle": "candle",
  "minecraft:candle_cake": "cloth",
  "minecraft:carpet": "cloth",
  "minecraft:carrots": "grass",
  "minecraft:cartography_table": "wood",
  "minecraft:carved_pumpkin": "wood",
  "minecraft:cave_vines": "cave_vines",
  "minecraft:cave_vines_body_with_berries": "cave_vines",
  "minecraft:cave_vines_head_with_berries": "cave_vines",
  "minecraft:chain": "chain",
  "minecraft:chain_command_block": "metal",
  "minecraft:cherry_button": "cherry_wood",
  "minecraft:cherry_door": "cherry_wood",
  "minecraft:cherry_double_slab": "cherry_wood",
  "minecraft:cherry_fence": "cherry_wood",
  "minecraft:cherry_fence_gate": "cherry_wood",
  "minecraft:cherry_hanging_sign": "cherry_wood_hanging_sign",
  "minecraft:cherry_leaves": "cherry_leaves",
  "minecraft:cherry_log": "cherry_wood",
  "minecraft:cherry_planks": "cherry_wood",
  "minecraft:cherry_pressure_plate": "cherry_wood",
  "minecraft:cherry_sapling": "bamboo_sapling",
  "minecraft:cherry_slab": "cherry_wood",
  "minecraft:cherry_stairs": "cherry_wood",
  "minecraft:cherry_standing_sign": "cherry_wood",
  "minecraft:cherry_trapdoor": "cherry_wood",
  "minecraft:cherry_wall_sign": "cherry_wood",
  "minecraft:cherry_wood": "cherry_wood",
  "minecraft:chest": "wood",
  "minecraft:chipped_anvil": "anvil",
  "minecraft:chiseled_bookshelf": "chiseled_bookshelf",
  "minecraft:chiseled_copper": "copper",
  "minecraft:chiseled_deepslate": "deepslate_bricks",
  "minecraft:chiseled_nether_bricks": "stone",
  "minecraft:chiseled_polished_blackstone": "stone",
  "minecraft:chiseled_quartz_block": "stone",
  "minecraft:chiseled_red_sandstone": "stone",
  "minecraft:chiseled_resin_bricks": "resin_brick",
  "minecraft:chiseled_sandstone": "stone",
  "minecraft:chiseled_stone_bricks": "stone",
  "minecraft:chiseled_tuff": "tuff",
  "minecraft:chiseled_tuff_bricks": "tuff_bricks",
  "minecraft:chorus_flower": "stone",
  "minecraft:chorus_plant": "stone",
  "minecraft:clay": "gravel",
  "minecraft:closed_eyeblossom": "eyeblossom",
  "minecraft:coal_block": "stone",
  "minecraft:coal_ore": "stone",
  "minecraft:coarse_dirt": "gravel",
  "minecraft:cobbled_deepslate": "deepslate",
  "minecraft:cobbled_deepslate_double_slab": "deepslate",
  "minecraft:cobbled_deepslate_slab": "deepslate",
  "minecraft:cobbled_deepslate_stairs": "deepslate",
  "minecraft:cobbled_deepslate_wall": "deepslate",
  "minecraft:cobblestone": "stone",
  "minecraft:cobblestone_double_slab": "stone",
  "minecraft:cobblestone_slab": "stone",
  "minecraft:cobblestone_wall": "stone",
  "minecraft:cocoa": "wood",
  "minecraft:command_block": "metal",
  "minecraft:composter": "wood",
  "minecraft:concrete": "stone",
  "minecraft:concretePowder": "sand",
  "minecraft:conduit": "stone",
  "minecraft:copper_block": "copper",
  "minecraft:copper_bulb": "copper_bulb",
  "minecraft:copper_door": "copper",
  "minecraft:copper_grate": "copper_grate",
  "minecraft:copper_ore": "stone",
  "minecraft:copper_trapdoor": "copper",
  "minecraft:coral": "stone",
  "minecraft:coral_fan": "stone",
  "minecraft:coral_fan_dead": "stone",
  "minecraft:coral_fan_hang": "stone",
  "minecraft:coral_fan_hang2": "stone",
  "minecraft:coral_fan_hang3": "stone",
  "minecraft:cornflower": "grass",
  "minecraft:cracked_deepslate_bricks": "deepslate_bricks",
  "minecraft:cracked_deepslate_tiles": "deepslate_bricks",
  "minecraft:cracked_nether_bricks": "stone",
  "minecraft:cracked_polished_blackstone_bricks": "stone",
  "minecraft:cracked_stone_bricks": "stone",
  "minecraft:crafter": "stone",
  "minecraft:crafting_table": "wood",
  "minecraft:creaking_heart": "creaking_heart",
  "minecraft:creeper_head": "stone",
  "minecraft:crimson_button": "nether_wood",
  "minecraft:crimson_door": "nether_wood",
  "minecraft:crimson_double_slab": "nether_wood",
  "minecraft:crimson_fence": "nether_wood",
  "minecraft:crimson_fence_gate": "nether_wood",
  "minecraft:crimson_fungus": "fungus",
  "minecraft:crimson_hanging_sign": "nether_wood_hanging_sign",
  "minecraft:crimson_hyphae": "stem",
  "minecraft:crimson_nylium": "nylium",
  "minecraft:crimson_planks": "nether_wood",
  "minecraft:crimson_pressure_plate": "nether_wood",
  "minecraft:crimson_roots": "roots",
  "minecraft:crimson_slab": "nether_wood",
  "minecraft:crimson_stairs": "nether_wood",
  "minecraft:crimson_standing_sign": "nether_wood",
  "minecraft:crimson_stem": "stem",
  "minecraft:crimson_trapdoor": "nether_wood",
  "minecraft:crimson_wall_sign": "nether_wood",
  "minecraft:crying_obsidian": "stone",
  "minecraft:cut_copper": "copper",
  "minecraft:cut_copper_slab": "copper",
  "minecraft:cut_copper_stairs": "copper",
  "minecraft:cut_red_sandstone": "stone",
  "minecraft:cut_red_sandstone_slab": "stone",
  "minecraft:cut_sandstone": "stone",
  "minecraft:cut_sandstone_slab": "stone",
  "minecraft:cyan_candle": "candle",
  "minecraft:cyan_candle_cake": "cloth",
  "minecraft:cyan_carpet": "cloth",
  "minecraft:cyan_concrete": "stone",
  "minecraft:cyan_concrete_powder": "sand",
  "minecraft:cyan_glazed_terracotta": "stone",
  "minecraft:cyan_shulker_box": "stone",
  "minecraft:cyan_stained_glass": "glass",
  "minecraft:cyan_stained_glass_pane": "glass",
  "minecraft:cyan_terracotta": "stone",
  "minecraft:cyan_wool": "cloth",
  "minecraft:damaged_anvil": "anvil",
  "minecraft:dandelion": "grass",
  "minecraft:dark_oak_button": "wood",
  "minecraft:dark_oak_door": "wood",
  "minecraft:dark_oak_double_slab": "wood",
  "minecraft:dark_oak_fence": "wood",
  "minecraft:dark_oak_fence_gate": "wood",
  "minecraft:dark_oak_hanging_sign": "hanging_sign",
  "minecraft:dark_oak_leaves": "grass",
  "minecraft:dark_oak_log": "wood",
  "minecraft:dark_oak_pressure_plate": "wood",
  "minecraft:dark_oak_sapling": "grass",
  "minecraft:dark_oak_slab": "wood",
  "minecraft:dark_oak_stairs": "wood",
  "minecraft:dark_oak_trapdoor": "wood",
  "minecraft:dark_oak_wood": "wood",
  "minecraft:dark_prismarine": "stone",
  "minecraft:dark_prismarine_double_slab": "stone",
  "minecraft:dark_prismarine_slab": "stone",
  "minecraft:dark_prismarine_stairs": "stone",
  "minecraft:darkoak_standing_sign": "wood",
  "minecraft:darkoak_wall_sign": "wood",
  "minecraft:daylight_detector": "wood",
  "minecraft:daylight_detector_inverted": "wood",
  "minecraft:dead_brain_coral": "stone",
  "minecraft:dead_brain_coral_block": "stone",
  "minecraft:dead_brain_coral_fan": "stone",
  "minecraft:dead_brain_coral_wall_fan": "stone",
  "minecraft:dead_bubble_coral": "stone",
  "minecraft:dead_bubble_coral_block": "stone",
  "minecraft:dead_bubble_coral_fan": "stone",
  "minecraft:dead_bubble_coral_wall_fan": "stone",
  "minecraft:dead_fire_coral": "stone",
  "minecraft:dead_fire_coral_block": "stone",
  "minecraft:dead_fire_coral_fan": "stone",
  "minecraft:dead_fire_coral_wall_fan": "stone",
  "minecraft:dead_horn_coral": "stone",
  "minecraft:dead_horn_coral_block": "stone",
  "minecraft:dead_horn_coral_fan": "stone",
  "minecraft:dead_horn_coral_wall_fan": "stone",
  "minecraft:dead_tube_coral": "stone",
  "minecraft:dead_tube_coral_block": "stone",
  "minecraft:dead_tube_coral_fan": "stone",
  "minecraft:dead_tube_coral_wall_fan": "stone",
  "minecraft:deadbush": "grass",
  "minecraft:decorated_pot": "decorated_pot",
  "minecraft:deepslate": "deepslate",
  "minecraft:deepslate_brick_double_slab": "deepslate_bricks",
  "minecraft:deepslate_brick_slab": "deepslate_bricks",
  "minecraft:deepslate_brick_stairs": "deepslate_bricks",
  "minecraft:deepslate_brick_wall": "deepslate_bricks",
  "minecraft:deepslate_bricks": "deepslate_bricks",
  "minecraft:deepslate_coal_ore": "deepslate",
  "minecraft:deepslate_copper_ore": "deepslate",
  "minecraft:deepslate_diamond_ore": "deepslate",
  "minecraft:deepslate_emerald_ore": "deepslate",
  "minecraft:deepslate_gold_ore": "deepslate",
  "minecraft:deepslate_iron_ore": "deepslate",
  "minecraft:deepslate_lapis_ore": "deepslate",
  "minecraft:deepslate_redstone_ore": "deepslate",
  "minecraft:deepslate_tile_double_slab": "deepslate_bricks",
  "minecraft:deepslate_tile_slab": "deepslate_bricks",
  "minecraft:deepslate_tile_stairs": "deepslate_bricks",
  "minecraft:deepslate_tile_wall": "deepslate_bricks",
  "minecraft:deepslate_tiles": "deepslate_bricks",
  "minecraft:deny": "stone",
  "minecraft:deprecated_anvil": "anvil",
  "minecraft:deprecated_purpur_block_1": "stone",
  "minecraft:deprecated_purpur_block_2": "stone",
  "minecraft:detector_rail": "metal",
  "minecraft:diamond_block": "metal",
  "minecraft:diamond_ore": "stone",
  "minecraft:diorite": "stone",
  "minecraft:diorite_double_slab": "stone",
  "minecraft:diorite_slab": "stone",
  "minecraft:diorite_stairs": "stone",
  "minecraft:diorite_wall": "stone",
  "minecraft:dirt": "gravel",
  "minecraft:dirt_with_roots": "dirt_with_roots",
  "minecraft:dispenser": "stone",
  "minecraft:double_cut_copper_slab": "copper",
  "minecraft:double_plant": "grass",
  "minecraft:double_stone_slab": "stone",
  "minecraft:double_stone_slab2": "stone",
  "minecraft:double_stone_slab3": "stone",
  "minecraft:double_stone_slab4": "stone",
  "minecraft:double_wooden_slab": "wood",
  "minecraft:dragon_egg": "stone",
  "minecraft:dragon_head": "stone",
  "minecraft:dried_kelp_block": "grass",
  "minecraft:dripstone_block": "dripstone_block",
  "minecraft:dropper": "stone",
  "minecraft:emerald_block": "metal",
  "minecraft:emerald_ore": "stone",
  "minecraft:end_brick_stairs": "stone",
  "minecraft:end_bricks": "stone",
  "minecraft:end_portal_frame": "glass",
  "minecraft:end_rod": "wood",
  "minecraft:end_stone": "stone",
  "minecraft:end_stone_brick_double_slab": "stone",
  "minecraft:end_stone_brick_slab": "stone",
  "minecraft:end_stone_brick_wall": "stone",
  "minecraft:exposed_chiseled_copper": "copper",
  "minecraft:exposed_copper": "copper",
  "minecraft:exposed_copper_bulb": "copper_bulb",
  "minecraft:exposed_copper_door": "copper",
  "minecraft:exposed_copper_grate": "copper_grate",
  "minecraft:exposed_copper_trapdoor": "copper",
  "minecraft:exposed_cut_copper": "copper",
  "minecraft:exposed_cut_copper_slab": "copper",
  "minecraft:exposed_cut_copper_stairs": "copper",
  "minecraft:exposed_double_cut_copper_slab": "copper",
  "minecraft:farmland": "gravel",
  "minecraft:fence": "wood",
  "minecraft:fence_gate": "wood",
  "minecraft:fern": "grass",
  "minecraft:fire": "wood",
  "minecraft:fire_coral": "stone",
  "minecraft:fire_coral_block": "stone",
  "minecraft:fire_coral_fan": "stone",
  "minecraft:fire_coral_wall_fan": "stone",
  "minecraft:fletching_table": "wood",
  "minecraft:flowering_azalea": "azalea",
  "minecraft:frame": "itemframe",
  "minecraft:frog_spawn": "frog_spawn",
  "minecraft:frosted_ice": "glass",
  "minecraft:furnace": "stone",
  "minecraft:gilded_blackstone": "stone",
  "minecraft:glass": "glass",
  "minecraft:glass_pane": "glass",
  "minecraft:glow_frame": "itemframe",
  "minecraft:glow_lichen": "glow_lichen",
  "minecraft:glowingobsidian": "stone",
  "minecraft:glowstone": "glass",
  "minecraft:gold_block": "metal",
  "minecraft:gold_ore": "stone",
  "minecraft:golden_rail": "metal",
  "minecraft:granite": "stone",
  "minecraft:granite_double_slab": "stone",
  "minecraft:granite_slab": "stone",
  "minecraft:granite_stairs": "stone",
  "minecraft:granite_wall": "stone",
  "minecraft:grass": "grass",
  "minecraft:grass_path": "grass",
  "minecraft:gravel": "gravel",
  "minecraft:gray_candle": "candle",
  "minecraft:gray_candle_cake": "cloth",
  "minecraft:gray_carpet": "cloth",
  "minecraft:gray_concrete": "stone",
  "minecraft:gray_concrete_powder": "sand",
  "minecraft:gray_glazed_terracotta": "stone",
  "minecraft:gray_shulker_box": "stone",
  "minecraft:gray_stained_glass": "glass",
  "minecraft:gray_stained_glass_pane": "glass",
  "minecraft:gray_terracotta": "stone",
  "minecraft:gray_wool": "cloth",
  "minecraft:green_candle": "candle",
  "minecraft:green_candle_cake": "cloth",
  "minecraft:green_carpet": "cloth",
  "minecraft:green_concrete": "stone",
  "minecraft:green_concrete_powder": "sand",
  "minecraft:green_glazed_terracotta": "stone",
  "minecraft:green_shulker_box": "stone",
  "minecraft:green_stained_glass": "glass",
  "minecraft:green_stained_glass_pane": "glass",
  "minecraft:green_terracotta": "stone",
  "minecraft:green_wool": "cloth",
  "minecraft:grindstone": "stone",
  "minecraft:hanging_roots": "hanging_roots",
  "minecraft:hardened_clay": "stone",
  "minecraft:hay_block": "grass",
  "minecraft:heavy_core": "heavy_core",
  "minecraft:heavy_weighted_pressure_plate": "metal",
  "minecraft:honey_block": "honey_block",
  "minecraft:honeycomb_block": "coral",
  "minecraft:hopper": "metal",
  "minecraft:horn_coral": "stone",
  "minecraft:horn_coral_block": "stone",
  "minecraft:horn_coral_fan": "stone",
  "minecraft:horn_coral_wall_fan": "stone",
  "minecraft:ice": "glass",
  "minecraft:infested_chiseled_stone_bricks": "stone",
  "minecraft:infested_cobblestone": "stone",
  "minecraft:infested_cracked_stone_bricks": "stone",
  "minecraft:infested_deepslate": "deepslate",
  "minecraft:infested_mossy_stone_bricks": "stone",
  "minecraft:infested_stone": "stone",
  "minecraft:infested_stone_bricks": "stone",
  "minecraft:info_update": "gravel",
  "minecraft:info_update2": "gravel",
  "minecraft:iron_bars": "metal",
  "minecraft:iron_block": "metal",
  "minecraft:iron_door": "metal",
  "minecraft:iron_ore": "stone",
  "minecraft:iron_trapdoor": "metal",
  "minecraft:jukebox": "wood",
  "minecraft:jungle_button": "wood",
  "minecraft:jungle_door": "wood",
  "minecraft:jungle_double_slab": "wood",
  "minecraft:jungle_fence": "wood",
  "minecraft:jungle_fence_gate": "wood",
  "minecraft:jungle_hanging_sign": "hanging_sign",
  "minecraft:jungle_leaves": "grass",
  "minecraft:jungle_log": "wood",
  "minecraft:jungle_pressure_plate": "wood",
  "minecraft:jungle_sapling": "grass",
  "minecraft:jungle_slab": "wood",
  "minecraft:jungle_stairs": "wood",
  "minecraft:jungle_standing_sign": "wood",
  "minecraft:jungle_trapdoor": "wood",
  "minecraft:jungle_wall_sign": "wood",
  "minecraft:jungle_wood": "wood",
  "minecraft:kelp": "grass",
  "minecraft:ladder": "ladder",
  "minecraft:lantern": "lantern",
  "minecraft:lapis_block": "stone",
  "minecraft:lapis_ore": "stone",
  "minecraft:large_amethyst_bud": "large_amethyst_bud",
  "minecraft:large_fern": "grass",
  "minecraft:leaves": "grass",
  "minecraft:leaves2": "grass",
  "minecraft:lectern": "wood",
  "minecraft:lever": "lever",
  "minecraft:light_block_0": "stone",
  "minecraft:light_block_1": "stone",
  "minecraft:light_block_10": "stone",
  "minecraft:light_block_11": "stone",
  "minecraft:light_block_12": "stone",
  "minecraft:light_block_13": "stone",
  "minecraft:light_block_14": "stone",
  "minecraft:light_block_15": "stone",
  "minecraft:light_block_2": "stone",
  "minecraft:light_block_3": "stone",
  "minecraft:light_block_4": "stone",
  "minecraft:light_block_5": "stone",
  "minecraft:light_block_6": "stone",
  "minecraft:light_block_7": "stone",
  "minecraft:light_block_8": "stone",
  "minecraft:light_block_9": "stone",
  "minecraft:light_blue_candle": "candle",
  "minecraft:light_blue_candle_cake": "cloth",
  "minecraft:light_blue_carpet": "cloth",
  "minecraft:light_blue_concrete": "stone",
  "minecraft:light_blue_concrete_powder": "sand",
  "minecraft:light_blue_glazed_terracotta": "stone",
  "minecraft:light_blue_shulker_box": "stone",
  "minecraft:light_blue_stained_glass": "glass",
  "minecraft:light_blue_stained_glass_pane": "glass",
  "minecraft:light_blue_terracotta": "stone",
  "minecraft:light_blue_wool": "cloth",
  "minecraft:light_gray_candle": "candle",
  "minecraft:light_gray_candle_cake": "cloth",
  "minecraft:light_gray_carpet": "cloth",
  "minecraft:light_gray_concrete": "stone",
  "minecraft:light_gray_concrete_powder": "sand",
  "minecraft:light_gray_shulker_box": "stone",
  "minecraft:light_gray_stained_glass": "glass",
  "minecraft:light_gray_stained_glass_pane": "glass",
  "minecraft:light_gray_terracotta": "stone",
  "minecraft:light_gray_wool": "cloth",
  "minecraft:light_weighted_pressure_plate": "metal",
  "minecraft:lightning_rod": "copper",
  "minecraft:lilac": "grass",
  "minecraft:lily_of_the_valley": "grass",
  "minecraft:lime_candle": "candle",
  "minecraft:lime_candle_cake": "cloth",
  "minecraft:lime_carpet": "cloth",
  "minecraft:lime_concrete": "stone",
  "minecraft:lime_concrete_powder": "sand",
  "minecraft:lime_glazed_terracotta": "stone",
  "minecraft:lime_shulker_box": "stone",
  "minecraft:lime_stained_glass": "glass",
  "minecraft:lime_stained_glass_pane": "glass",
  "minecraft:lime_terracotta": "stone",
  "minecraft:lime_wool": "cloth",
  "minecraft:lit_blast_furnace": "stone",
  "minecraft:lit_deepslate_redstone_ore": "deepslate",
  "minecraft:lit_furnace": "stone",
  "minecraft:lit_pumpkin": "wood",
  "minecraft:lit_redstone_lamp": "glass",
  "minecraft:lit_redstone_ore": "stone",
  "minecraft:lit_smoker": "stone",
  "minecraft:lodestone": "lodestone",
  "minecraft:log": "wood",
  "minecraft:log2": "wood",
  "minecraft:loom": "wood",
  "minecraft:magenta_candle": "candle",
  "minecraft:magenta_candle_cake": "cloth",
  "minecraft:magenta_carpet": "cloth",
  "minecraft:magenta_concrete": "stone",
  "minecraft:magenta_concrete_powder": "sand",
  "minecraft:magenta_glazed_terracotta": "stone",
  "minecraft:magenta_shulker_box": "stone",
  "minecraft:magenta_stained_glass": "glass",
  "minecraft:magenta_stained_glass_pane": "glass",
  "minecraft:magenta_terracotta": "stone",
  "minecraft:magenta_wool": "cloth",
  "minecraft:magma": "stone",
  "minecraft:mangrove_button": "wood",
  "minecraft:mangrove_door": "wood",
  "minecraft:mangrove_double_slab": "wood",
  "minecraft:mangrove_fence": "wood",
  "minecraft:mangrove_fence_gate": "wood",
  "minecraft:mangrove_hanging_sign": "hanging_sign",
  "minecraft:mangrove_leaves": "grass",
  "minecraft:mangrove_log": "wood",
  "minecraft:mangrove_planks": "wood",
  "minecraft:mangrove_pressure_plate": "wood",
  "minecraft:mangrove_propagule": "grass",
  "minecraft:mangrove_roots": "mangrove_roots",
  "minecraft:mangrove_slab": "wood",
  "minecraft:mangrove_stairs": "wood",
  "minecraft:mangrove_standing_sign": "wood",
  "minecraft:mangrove_trapdoor": "wood",
  "minecraft:mangrove_wall_sign": "wood",
  "minecraft:mangrove_wood": "wood",
  "minecraft:medium_amethyst_bud": "medium_amethyst_bud",
  "minecraft:melon_block": "wood",
  "minecraft:melon_stem": "wood",
  "minecraft:mob_spawner": "mob_spawner",
  "minecraft:moss_block": "moss_block",
  "minecraft:moss_carpet": "moss_carpet",
  "minecraft:mossy_cobblestone": "stone",
  "minecraft:mossy_cobblestone_double_slab": "stone",
  "minecraft:mossy_cobblestone_slab": "stone",
  "minecraft:mossy_cobblestone_stairs": "stone",
  "minecraft:mossy_cobblestone_wall": "stone",
  "minecraft:mossy_stone_brick_slab": "stone",
  "minecraft:mossy_stone_brick_stairs": "stone",
  "minecraft:mossy_stone_brick_wall": "stone",
  "minecraft:mossy_stone_bricks": "stone",
  "minecraft:mud": "mud",
  "minecraft:mud_brick_double_slab": "mud_bricks",
  "minecraft:mud_brick_slab": "mud_bricks",
  "minecraft:mud_brick_stairs": "mud_bricks",
  "minecraft:mud_brick_wall": "mud_bricks",
  "minecraft:mud_bricks": "mud_bricks",
  "minecraft:muddy_mangrove_roots": "muddy_mangrove_roots",
  "minecraft:mushroom_stem": "wood",
  "minecraft:mycelium": "grass",
  "minecraft:nether_brick": "nether_brick",
  "minecraft:nether_brick_double_slab": "stone",
  "minecraft:nether_brick_fence": "nether_brick",
  "minecraft:nether_brick_slab": "stone",
  "minecraft:nether_brick_stairs": "nether_brick",
  "minecraft:nether_brick_wall": "stone",
  "minecraft:nether_gold_ore": "nether_gold_ore",
  "minecraft:nether_sprouts": "nether_sprouts",
  "minecraft:nether_wart": "nether_wart",
  "minecraft:nether_wart_block": "nether_wart",
  "minecraft:netherite_block": "netherite",
  "minecraft:netherrack": "netherrack",
  "minecraft:netherreactor": "metal",
  "minecraft:normal_stone_slab": "stone",
  "minecraft:normal_stone_stairs": "stone",
  "minecraft:noteblock": "wood",
  "minecraft:oak_double_slab": "wood",
  "minecraft:oak_fence": "wood",
  "minecraft:oak_hanging_sign": "hanging_sign",
  "minecraft:oak_leaves": "grass",
  "minecraft:oak_log": "wood",
  "minecraft:oak_sapling": "grass",
  "minecraft:oak_slab": "wood",
  "minecraft:oak_stairs": "wood",
  "minecraft:oak_wood": "wood",
  "minecraft:observer": "metal",
  "minecraft:obsidian": "stone",
  "minecraft:ochre_froglight": "froglight",
  "minecraft:open_eyeblossom": "eyeblossom",
  "minecraft:orange_candle": "candle",
  "minecraft:orange_candle_cake": "cloth",
  "minecraft:orange_carpet": "cloth",
  "minecraft:orange_concrete": "stone",
  "minecraft:orange_concrete_powder": "sand",
  "minecraft:orange_glazed_terracotta": "stone",
  "minecraft:orange_shulker_box": "stone",
  "minecraft:orange_stained_glass": "glass",
  "minecraft:orange_stained_glass_pane": "glass",
  "minecraft:orange_terracotta": "stone",
  "minecraft:orange_tulip": "grass",
  "minecraft:orange_wool": "cloth",
  "minecraft:oxeye_daisy": "grass",
  "minecraft:oxidized_chiseled_copper": "copper",
  "minecraft:oxidized_copper": "copper",
  "minecraft:oxidized_copper_bulb": "copper_bulb",
  "minecraft:oxidized_copper_door": "copper",
  "minecraft:oxidized_copper_grate": "copper_grate",
  "minecraft:oxidized_copper_trapdoor": "copper",
  "minecraft:oxidized_cut_copper": "copper",
  "minecraft:oxidized_cut_copper_slab": "copper",
  "minecraft:oxidized_cut_copper_stairs": "copper",
  "minecraft:oxidized_double_cut_copper_slab": "copper",
  "minecraft:packed_ice": "glass",
  "minecraft:packed_mud": "packed_mud",
  "minecraft:pale_hanging_moss": "pale_hanging_moss",
  "minecraft:pale_moss_block": "moss_block",
  "minecraft:pale_moss_carpet": "moss_carpet",
  "minecraft:pale_oak_button": "wood",
  "minecraft:pale_oak_door": "wood",
  "minecraft:pale_oak_double_slab": "wood",
  "minecraft:pale_oak_fence": "wood",
  "minecraft:pale_oak_fence_gate": "wood",
  "minecraft:pale_oak_hanging_sign": "hanging_sign",
  "minecraft:pale_oak_leaves": "grass",
  "minecraft:pale_oak_log": "wood",
  "minecraft:pale_oak_planks": "wood",
  "minecraft:pale_oak_pressure_plate": "wood",
  "minecraft:pale_oak_sapling": "grass",
  "minecraft:pale_oak_slab": "wood",
  "minecraft:pale_oak_stairs": "wood",
  "minecraft:pale_oak_standing_sign": "wood",
  "minecraft:pale_oak_trapdoor": "wood",
  "minecraft:pale_oak_wall_sign": "wood",
  "minecraft:pale_oak_wood": "wood",
  "minecraft:pearlescent_froglight": "froglight",
  "minecraft:peony": "grass",
  "minecraft:petrified_oak_double_slab": "stone",
  "minecraft:petrified_oak_slab": "stone",
  "minecraft:piglin_head": "stone",
  "minecraft:pink_candle": "candle",
  "minecraft:pink_candle_cake": "cloth",
  "minecraft:pink_carpet": "cloth",
  "minecraft:pink_concrete": "stone",
  "minecraft:pink_concrete_powder": "sand",
  "minecraft:pink_glazed_terracotta": "stone",
  "minecraft:pink_petals": "pink_petals",
  "minecraft:pink_shulker_box": "stone",
  "minecraft:pink_stained_glass": "glass",
  "minecraft:pink_stained_glass_pane": "glass",
  "minecraft:pink_terracotta": "stone",
  "minecraft:pink_tulip": "grass",
  "minecraft:pink_wool": "cloth",
  "minecraft:piston": "stone",
  "minecraft:pitcher_crop": "grass",
  "minecraft:pitcher_plant": "grass",
  "minecraft:planks": "wood",
  "minecraft:player_head": "stone",
  "minecraft:podzol": "gravel",
  "minecraft:pointed_dripstone": "pointed_dripstone",
  "minecraft:polished_andesite": "stone",
  "minecraft:polished_andesite_double_slab": "stone",
  "minecraft:polished_andesite_slab": "stone",
  "minecraft:polished_andesite_stairs": "stone",
  "minecraft:polished_basalt": "basalt",
  "minecraft:polished_blackstone": "stone",
  "minecraft:polished_blackstone_brick_double_slab": "stone",
  "minecraft:polished_blackstone_brick_slab": "stone",
  "minecraft:polished_blackstone_brick_stairs": "stone",
  "minecraft:polished_blackstone_brick_wall": "stone",
  "minecraft:polished_blackstone_bricks": "stone",
  "minecraft:polished_blackstone_button": "stone",
  "minecraft:polished_blackstone_double_slab": "stone",
  "minecraft:polished_blackstone_pressure_plate": "stone",
  "minecraft:polished_blackstone_slab": "stone",
  "minecraft:polished_blackstone_stairs": "stone",
  "minecraft:polished_blackstone_wall": "stone",
  "minecraft:polished_deepslate": "deepslate",
  "minecraft:polished_deepslate_double_slab": "deepslate",
  "minecraft:polished_deepslate_slab": "deepslate",
  "minecraft:polished_deepslate_stairs": "deepslate",
  "minecraft:polished_deepslate_wall": "deepslate",
  "minecraft:polished_diorite": "stone",
  "minecraft:polished_diorite_double_slab": "stone",
  "minecraft:polished_diorite_slab": "stone",
  "minecraft:polished_diorite_stairs": "stone",
  "minecraft:polished_granite": "stone",
  "minecraft:polished_granite_double_slab": "stone",
  "minecraft:polished_granite_slab": "stone",
  "minecraft:polished_granite_stairs": "stone",
  "minecraft:polished_tuff": "polished_tuff",
  "minecraft:polished_tuff_double_slab": "polished_tuff",
  "minecraft:polished_tuff_slab": "polished_tuff",
  "minecraft:polished_tuff_stairs": "polished_tuff",
  "minecraft:polished_tuff_wall": "polished_tuff",
  "minecraft:poppy": "grass",
  "minecraft:portal": "glass",
  "minecraft:potatoes": "grass",
  "minecraft:powder_snow": "powder_snow",
  "minecraft:powered_comparator": "wood",
  "minecraft:powered_repeater": "wood",
  "minecraft:prismarine": "stone",
  "minecraft:prismarine_brick_double_slab": "stone",
  "minecraft:prismarine_brick_slab": "stone",
  "minecraft:prismarine_bricks": "stone",
  "minecraft:prismarine_bricks_stairs": "stone",
  "minecraft:prismarine_double_slab": "stone",
  "minecraft:prismarine_slab": "stone",
  "minecraft:prismarine_stairs": "stone",
  "minecraft:prismarine_wall": "stone",
  "minecraft:pumpkin": "wood",
  "minecraft:pumpkin_stem": "wood",
  "minecraft:purple_candle": "candle",
  "minecraft:purple_candle_cake": "cloth",
  "minecraft:purple_carpet": "cloth",
  "minecraft:purple_concrete": "stone",
  "minecraft:purple_concrete_powder": "sand",
  "minecraft:purple_glazed_terracotta": "stone",
  "minecraft:purple_shulker_box": "stone",
  "minecraft:purple_stained_glass": "glass",
  "minecraft:purple_stained_glass_pane": "glass",
  "minecraft:purple_terracotta": "stone",
  "minecraft:purple_wool": "cloth",
  "minecraft:purpur_block": "stone",
  "minecraft:purpur_double_slab": "stone",
  "minecraft:purpur_pillar": "stone",
  "minecraft:purpur_slab": "stone",
  "minecraft:quartz_block": "stone",
  "minecraft:quartz_bricks": "stone",
  "minecraft:quartz_double_slab": "stone",
  "minecraft:quartz_ore": "nether_gold_ore",
  "minecraft:quartz_pillar": "stone",
  "minecraft:quartz_slab": "stone",
  "minecraft:rail": "metal",
  "minecraft:raw_copper_block": "stone",
  "minecraft:raw_gold_block": "stone",
  "minecraft:raw_iron_block": "stone",
  "minecraft:red_candle": "candle",
  "minecraft:red_candle_cake": "cloth",
  "minecraft:red_carpet": "cloth",
  "minecraft:red_concrete": "stone",
  "minecraft:red_concrete_powder": "sand",
  "minecraft:red_flower": "grass",
  "minecraft:red_glazed_terracotta": "stone",
  "minecraft:red_mushroom": "grass",
  "minecraft:red_mushroom_block": "wood",
  "minecraft:red_nether_brick": "nether_brick",
  "minecraft:red_nether_brick_double_slab": "stone",
  "minecraft:red_nether_brick_slab": "stone",
  "minecraft:red_nether_brick_stairs": "nether_brick",
  "minecraft:red_nether_brick_wall": "stone",
  "minecraft:red_sand": "sand",
  "minecraft:red_sandstone": "stone",
  "minecraft:red_sandstone_double_slab": "stone",
  "minecraft:red_sandstone_slab": "stone",
  "minecraft:red_sandstone_wall": "stone",
  "minecraft:red_shulker_box": "stone",
  "minecraft:red_stained_glass": "glass",
  "minecraft:red_stained_glass_pane": "glass",
  "minecraft:red_terracotta": "stone",
  "minecraft:red_tulip": "grass",
  "minecraft:red_wool": "cloth",
  "minecraft:redstone_block": "stone",
  "minecraft:redstone_lamp": "glass",
  "minecraft:redstone_ore": "stone",
  "minecraft:redstone_torch": "wood",
  "minecraft:reeds": "grass",
  "minecraft:reinforced_deepslate": "deepslate",
  "minecraft:repeating_command_block": "metal",
  "minecraft:resin_block": "resin",
  "minecraft:resin_brick_double_slab": "resin_brick",
  "minecraft:resin_brick_slab": "resin_brick",
  "minecraft:resin_brick_stairs": "resin_brick",
  "minecraft:resin_brick_wall": "resin_brick",
  "minecraft:resin_bricks": "resin_brick",
  "minecraft:resin_clump": "resin",
  "minecraft:respawn_anchor": "metal",
  "minecraft:rose_bush": "grass",
  "minecraft:sand": "sand",
  "minecraft:sandstone": "stone",
  "minecraft:sandstone_double_slab": "stone",
  "minecraft:sandstone_slab": "stone",
  "minecraft:sandstone_wall": "stone",
  "minecraft:sapling": "grass",
  "minecraft:scaffolding": "scaffolding",
  "minecraft:sculk": "sculk",
  "minecraft:sculk_catalyst": "sculk_catalyst",
  "minecraft:sculk_sensor": "sculk_sensor",
  "minecraft:sculk_shrieker": "sculk_shrieker",
  "minecraft:sculk_vein": "sculk_vein",
  "minecraft:seaLantern": "glass",
  "minecraft:sea_pickle": "slime",
  "minecraft:seagrass": "grass",
  "minecraft:short_grass": "grass",
  "minecraft:shroomlight": "shroomlight",
  "minecraft:shulker_box": "stone",
  "minecraft:silver_glazed_terracotta": "stone",
  "minecraft:skeleton_skull": "stone",
  "minecraft:skull": "stone",
  "minecraft:slime": "slime",
  "minecraft:small_amethyst_bud": "small_amethyst_bud",
  "minecraft:small_dripleaf_block": "big_dripleaf",
  "minecraft:smithing_table": "wood",
  "minecraft:smoker": "stone",
  "minecraft:smooth_basalt": "basalt",
  "minecraft:smooth_quartz": "stone",
  "minecraft:smooth_quartz_slab": "stone",
  "minecraft:smooth_quartz_stairs": "stone",
  "minecraft:smooth_red_sandstone": "stone",
  "minecraft:smooth_red_sandstone_double_slab": "stone",
  "minecraft:smooth_red_sandstone_slab": "stone",
  "minecraft:smooth_red_sandstone_stairs": "stone",
  "minecraft:smooth_sandstone": "stone",
  "minecraft:smooth_sandstone_double_slab": "stone",
  "minecraft:smooth_sandstone_slab": "stone",
  "minecraft:smooth_sandstone_stairs": "stone",
  "minecraft:smooth_stone": "stone",
  "minecraft:smooth_stone_double_slab": "stone",
  "minecraft:smooth_stone_slab": "stone",
  "minecraft:sniffer_egg": "metal",
  "minecraft:snow": "snow",
  "minecraft:snow_layer": "snow",
  "minecraft:soul_campfire": "wood",
  "minecraft:soul_fire": "stone",
  "minecraft:soul_lantern": "lantern",
  "minecraft:soul_sand": "soul_sand",
  "minecraft:soul_soil": "soul_soil",
  "minecraft:soul_torch": "wood",
  "minecraft:sponge": "sponge",
  "minecraft:spore_blossom": "spore_blossom",
  "minecraft:spruce_button": "wood",
  "minecraft:spruce_door": "wood",
  "minecraft:spruce_double_slab": "wood",
  "minecraft:spruce_fence": "wood",
  "minecraft:spruce_fence_gate": "wood",
  "minecraft:spruce_hanging_sign": "hanging_sign",
  "minecraft:spruce_leaves": "grass",
  "minecraft:spruce_log": "wood",
  "minecraft:spruce_pressure_plate": "wood",
  "minecraft:spruce_sapling": "grass",
  "minecraft:spruce_slab": "wood",
  "minecraft:spruce_stairs": "wood",
  "minecraft:spruce_standing_sign": "wood",
  "minecraft:spruce_trapdoor": "wood",
  "minecraft:spruce_wall_sign": "wood",
  "minecraft:spruce_wood": "wood",
  "minecraft:stained_glass": "glass",
  "minecraft:stained_glass_pane": "glass",
  "minecraft:stained_hardened_clay": "stone",
  "minecraft:standing_banner": "wood",
  "minecraft:standing_sign": "wood",
  "minecraft:sticky_piston": "stone",
  "minecraft:stone": "stone",
  "minecraft:stone_brick_double_slab": "stone",
  "minecraft:stone_brick_slab": "stone",
  "minecraft:stone_brick_wall": "stone",
  "minecraft:stone_bricks": "stone",
  "minecraft:stone_button": "stone",
  "minecraft:stone_pressure_plate": "stone",
  "minecraft:stone_slab": "stone",
  "minecraft:stone_slab2": "stone",
  "minecraft:stone_slab3": "stone",
  "minecraft:stone_slab4": "stone",
  "minecraft:stonebrick": "stone",
  "minecraft:stonecutter": "stone",
  "minecraft:stonecutter_block": "stone",
  "minecraft:stripped_acacia_log": "wood",
  "minecraft:stripped_acacia_wood": "wood",
  "minecraft:stripped_bamboo_block": "bamboo_wood",
  "minecraft:stripped_birch_log": "wood",
  "minecraft:stripped_birch_wood": "wood",
  "minecraft:stripped_cherry_log": "cherry_wood",
  "minecraft:stripped_cherry_wood": "cherry_wood",
  "minecraft:stripped_crimson_hyphae": "stem",
  "minecraft:stripped_crimson_stem": "stem",
  "minecraft:stripped_dark_oak_log": "wood",
  "minecraft:stripped_dark_oak_wood": "wood",
  "minecraft:stripped_jungle_log": "wood",
  "minecraft:stripped_jungle_wood": "wood",
  "minecraft:stripped_mangrove_log": "wood",
  "minecraft:stripped_mangrove_wood": "wood",
  "minecraft:stripped_oak_log": "wood",
  "minecraft:stripped_oak_wood": "wood",
  "minecraft:stripped_pale_oak_log": "wood",
  "minecraft:stripped_pale_oak_wood": "wood",
  "minecraft:stripped_spruce_log": "wood",
  "minecraft:stripped_spruce_wood": "wood",
  "minecraft:stripped_warped_hyphae": "stem",
  "minecraft:stripped_warped_stem": "stem",
  "minecraft:sunflower": "grass",
  "minecraft:suspicious_gravel": "suspicious_gravel",
  "minecraft:suspicious_sand": "suspicious_sand",
  "minecraft:sweet_berry_bush": "sweet_berry_bush",
  "minecraft:tall_grass": "grass",
  "minecraft:tallgrass": "grass",
  "minecraft:target": "grass",
  "minecraft:tinted_glass": "glass",
  "minecraft:tnt": "grass",
  "minecraft:torch": "wood",
  "minecraft:torchflower": "grass",
  "minecraft:torchflower_crop": "grass",
  "minecraft:trapdoor": "wood",
  "minecraft:trapped_chest": "wood",
  "minecraft:trial_spawner": "trial_spawner",
  "minecraft:tube_coral": "stone",
  "minecraft:tube_coral_block": "stone",
  "minecraft:tube_coral_fan": "stone",
  "minecraft:tube_coral_wall_fan": "stone",
  "minecraft:tuff": "tuff",
  "minecraft:tuff_brick_double_slab": "tuff_bricks",
  "minecraft:tuff_brick_slab": "tuff_bricks",
  "minecraft:tuff_brick_stairs": "tuff_bricks",
  "minecraft:tuff_brick_wall": "tuff_bricks",
  "minecraft:tuff_bricks": "tuff_bricks",
  "minecraft:tuff_double_slab": "tuff",
  "minecraft:tuff_slab": "tuff",
  "minecraft:tuff_stairs": "tuff",
  "minecraft:tuff_wall": "tuff",
  "minecraft:turtle_egg": "turtle_egg",
  "minecraft:twisting_vines": "vines",
  "minecraft:undyed_shulker_box": "stone",
  "minecraft:unlit_redstone_torch": "wood",
  "minecraft:unpowered_comparator": "comparator",
  "minecraft:unpowered_repeater": "wood",
  "minecraft:vault": "vault",
  "minecraft:verdant_froglight": "froglight",
  "minecraft:vine": "vines",
  "minecraft:wall_banner": "wood",
  "minecraft:wall_sign": "wood",
  "minecraft:warped_button": "nether_wood",
  "minecraft:warped_door": "nether_wood",
  "minecraft:warped_double_slab": "nether_wood",
  "minecraft:warped_fence": "nether_wood",
  "minecraft:warped_fence_gate": "nether_wood",
  "minecraft:warped_fungus": "fungus",
  "minecraft:warped_hanging_sign": "nether_wood_hanging_sign",
  "minecraft:warped_hyphae": "stem",
  "minecraft:warped_nylium": "nylium",
  "minecraft:warped_planks": "nether_wood",
  "minecraft:warped_pressure_plate": "nether_wood",
  "minecraft:warped_roots": "roots",
  "minecraft:warped_slab": "nether_wood",
  "minecraft:warped_stairs": "nether_wood",
  "minecraft:warped_standing_sign": "nether_wood",
  "minecraft:warped_stem": "stem",
  "minecraft:warped_trapdoor": "nether_wood",
  "minecraft:warped_wall_sign": "nether_wood",
  "minecraft:warped_wart_block": "nether_wart",
  "minecraft:waterlily": "grass",
  "minecraft:waxed_chiseled_copper": "copper",
  "minecraft:waxed_copper": "copper",
  "minecraft:waxed_copper_bulb": "copper_bulb",
  "minecraft:waxed_copper_door": "copper",
  "minecraft:waxed_copper_grate": "copper_grate",
  "minecraft:waxed_copper_trapdoor": "copper",
  "minecraft:waxed_cut_copper": "copper",
  "minecraft:waxed_cut_copper_slab": "copper",
  "minecraft:waxed_cut_copper_stairs": "copper",
  "minecraft:waxed_double_cut_copper_slab": "copper",
  "minecraft:waxed_exposed_chiseled_copper": "copper",
  "minecraft:waxed_exposed_copper": "copper",
  "minecraft:waxed_exposed_copper_bulb": "copper_bulb",
  "minecraft:waxed_exposed_copper_door": "copper",
  "minecraft:waxed_exposed_copper_grate": "copper_grate",
  "minecraft:waxed_exposed_copper_trapdoor": "copper",
  "minecraft:waxed_exposed_cut_copper": "copper",
  "minecraft:waxed_exposed_cut_copper_slab": "copper",
  "minecraft:waxed_exposed_cut_copper_stairs": "copper",
  "minecraft:waxed_exposed_double_cut_copper_slab": "copper",
  "minecraft:waxed_oxidized_chiseled_copper": "copper",
  "minecraft:waxed_oxidized_copper": "copper",
  "minecraft:waxed_oxidized_copper_bulb": "copper_bulb",
  "minecraft:waxed_oxidized_copper_door": "copper",
  "minecraft:waxed_oxidized_copper_grate": "copper_grate",
  "minecraft:waxed_oxidized_copper_trapdoor": "copper",
  "minecraft:waxed_oxidized_cut_copper": "copper",
  "minecraft:waxed_oxidized_cut_copper_slab": "copper",
  "minecraft:waxed_oxidized_cut_copper_stairs": "copper",
  "minecraft:waxed_oxidized_double_cut_copper_slab": "copper",
  "minecraft:waxed_weathered_chiseled_copper": "copper",
  "minecraft:waxed_weathered_copper": "copper",
  "minecraft:waxed_weathered_copper_bulb": "copper_bulb",
  "minecraft:waxed_weathered_copper_door": "copper",
  "minecraft:waxed_weathered_copper_grate": "copper_grate",
  "minecraft:waxed_weathered_copper_trapdoor": "copper",
  "minecraft:waxed_weathered_cut_copper": "copper",
  "minecraft:waxed_weathered_cut_copper_slab": "copper",
  "minecraft:waxed_weathered_cut_copper_stairs": "copper",
  "minecraft:waxed_weathered_double_cut_copper_slab": "copper",
  "minecraft:weathered_chiseled_copper": "copper",
  "minecraft:weathered_copper": "copper",
  "minecraft:weathered_copper_bulb": "copper_bulb",
  "minecraft:weathered_copper_door": "copper",
  "minecraft:weathered_copper_grate": "copper_grate",
  "minecraft:weathered_copper_trapdoor": "copper",
  "minecraft:weathered_cut_copper": "copper",
  "minecraft:weathered_cut_copper_slab": "copper",
  "minecraft:weathered_cut_copper_stairs": "copper",
  "minecraft:weathered_double_cut_copper_slab": "copper",
  "minecraft:web": "web",
  "minecraft:weeping_vines": "vines",
  "minecraft:wet_sponge": "wet_sponge",
  "minecraft:wheat": "grass",
  "minecraft:white_candle": "candle",
  "minecraft:white_candle_cake": "cloth",
  "minecraft:white_carpet": "cloth",
  "minecraft:white_concrete": "stone",
  "minecraft:white_concrete_powder": "sand",
  "minecraft:white_glazed_terracotta": "stone",
  "minecraft:white_shulker_box": "stone",
  "minecraft:white_stained_glass": "glass",
  "minecraft:white_stained_glass_pane": "glass",
  "minecraft:white_terracotta": "stone",
  "minecraft:white_tulip": "grass",
  "minecraft:white_wool": "cloth",
  "minecraft:wither_rose": "grass",
  "minecraft:wither_skeleton_skull": "stone",
  "minecraft:wood": "wood",
  "minecraft:wooden_button": "wood",
  "minecraft:wooden_door": "wood",
  "minecraft:wooden_pressure_plate": "wood",
  "minecraft:wooden_slab": "wood",
  "minecraft:wool": "cloth",
  "minecraft:yellow_candle": "candle",
  "minecraft:yellow_candle_cake": "cloth",
  "minecraft:yellow_carpet": "cloth",
  "minecraft:yellow_concrete": "stone",
  "minecraft:yellow_concrete_powder": "sand",
  "minecraft:yellow_flower": "grass",
  "minecraft:yellow_glazed_terracotta": "stone",
  "minecraft:yellow_shulker_box": "stone",
  "minecraft:yellow_stained_glass": "glass",
  "minecraft:yellow_stained_glass_pane": "glass",
  "minecraft:yellow_terracotta": "stone",
  "minecraft:yellow_wool": "cloth",
  "minecraft:zombie_head": "stone"
}
